argparse_extensions/__init__.py
argparse_extensions/__version__.py
argparse_extensions/argparse_extensions.py
argparse_extensions-1.0.3.dist-info/METADATA
argparse_extensions-1.0.3.dist-info/RECORD
argparse_extensions-1.0.3.dist-info/WHEEL
argparse_extensions-1.0.3.dist-info/top_level.txt
