Metadata-Version: 2.1
Name: argparse-extensions
Version: 1.0.3
Summary: argparse extensions
Home-page: https://github.com/nkouevda/argparse-extensions
Author: Nikita Kouevda
Author-email: nkouevda@gmail.com
License: MIT
Platform: UNKNOWN
